darbia/shipping/types/__init__.py
darbia/shipping/types/models.py
darbia/shipping/types/py.typed
darbiadev_shipping_types-0.4.0.dist-info/LICENSE
darbiadev_shipping_types-0.4.0.dist-info/METADATA
darbiadev_shipping_types-0.4.0.dist-info/WHEEL
darbiadev_shipping_types-0.4.0.dist-info/top_level.txt
darbiadev_shipping_types-0.4.0.dist-info/RECORD
